gustav/__init__.py
gustav/dataTemplate_adaptive.py
gustav/gustav.py
gustav/utils.py
gustav/forms/__init__.py
gustav/forms/lateralization.py
gustav/forms/localization.py
gustav/forms/nafc.py
gustav/forms/rt.py
gustav/forms/speech.py
gustav/frontends/__init__.py
gustav/frontends/term.py
gustav/frontends/tk.py
gustav/methods/__init__.py
gustav/methods/adaptive.py
gustav/methods/constant.py
gustav/methods/pest.py
gustav/user_scripts/gustav_exp__adaptive__frequency_discrim.py
gustav/user_scripts/gustav_exp__adaptive_quietthresholds.py
gustav/user_scripts/gustav_exp__lateralization.py
gustav-0.8.2.dist-info/LICENSE.md
gustav-0.8.2.dist-info/METADATA
gustav-0.8.2.dist-info/WHEEL
gustav-0.8.2.dist-info/top_level.txt
gustav-0.8.2.dist-info/RECORD
